{
  "kind": "Listing",
  "data": {
    "modhash": "oo6ngy5xdg5cea139c6b0c6968e88495e138cd47d2450ad3c8",
    "children": [
      {
        "kind": "t3",
        "data": {
          "domain": "portsherry.com",
          "banned_by": null,
          "media_embed": {},
          "subreddit": "comics",
          "selftext_html": null,
          "selftext": "",
          "likes": null,
          "suggested_sort": null,
          "user_reports": [],
          "secure_media": null,
          "link_flair_text": null,
          "id": "3ingwq",
          "from_kind": null,
          "gilded": 0,
          "archived": false,
          "clicked": false,
          "report_reasons": null,
          "author": "patty_kerry",
          "media": null,
          "score": 5,
          "approved_by": null,
          "over_18": false,
          "hidden": false,
          "preview": {
            "images": [
              {
                "source": {
                  "url": "https://i.redditmedia.com/O7LVbThYMsVFNbeH7LV2ZpMHwl4Nbcw83VcdZQoq78c.jpg?s=19d03bafb77f6417638a91c1a9364aab",
                  "width": 500,
                  "height": 328
                },
                "resolutions": [
                  {
                    "url": "https://i.redditmedia.com/O7LVbThYMsVFNbeH7LV2ZpMHwl4Nbcw83VcdZQoq78c.jpg?fit=crop&amp;crop=faces%2Centropy&amp;arh=2&amp;w=108&amp;s=bef4668759f7c80bae46de9bf1d9ef4a",
                    "width": 108,
                    "height": 70
                  },
                  {
                    "url": "https://i.redditmedia.com/O7LVbThYMsVFNbeH7LV2ZpMHwl4Nbcw83VcdZQoq78c.jpg?fit=crop&amp;crop=faces%2Centropy&amp;arh=2&amp;w=216&amp;s=c2c241801dd8f4a1a26d7afa9ef061ff",
                    "width": 216,
                    "height": 141
                  },
                  {
                    "url": "https://i.redditmedia.com/O7LVbThYMsVFNbeH7LV2ZpMHwl4Nbcw83VcdZQoq78c.jpg?fit=crop&amp;crop=faces%2Centropy&amp;arh=2&amp;w=320&amp;s=8da9d0e73fa1575c9815b6d3f36c90f8",
                    "width": 320,
                    "height": 209
                  }
                ],
                "variants": {},
                "id": "vyiP8jFmR1XUsnKgb962_HJfda8oWw1hj4YRUpYSaIs"
              }
            ]
          },
          "num_comments": 0,
          "thumbnail": "http://b.thumbs.redditmedia.com/JcQNpAX6A11l5MtBRGVVMVdDG7oUGJhZkh5CeEb7BiE.jpg",
          "subreddit_id": "t5_2qh0s",
          "hide_score": false,
          "edited": false,
          "link_flair_css_class": null,
          "author_flair_css_class": null,
          "downs": 0,
          "secure_media_embed": {},
          "saved": false,
          "removal_reason": null,
          "post_hint": "link",
          "stickied": false,
          "from": null,
          "is_self": false,
          "from_id": null,
          "permalink": "/r/comics/comments/3ingwq/i_made_him_an_offering/",
          "name": "t3_3ingwq",
          "created": 1440741352.0,
          "url": "http://portsherry.com/comics/i-made-him-an-offering/",
          "author_flair_text": null,
          "quarantine": false,
          "title": "I made him an offering...",
          "created_utc": 1440712552.0,
          "distinguished": null,
          "mod_reports": [],
          "visited": false,
          "num_reports": null,
          "ups": 5
        }
      },
      {
        "kind": "t3",
        "data": {
          "domain": "userscloud.com",
          "banned_by": null,
          "media_embed": {},
          "subreddit": "comics",
          "selftext_html": null,
          "selftext": "",
          "likes": null,
          "suggested_sort": null,
          "user_reports": [],
          "secure_media": null,
          "link_flair_text": null,
          "id": "3ilvi0",
          "from_kind": null,
          "gilded": 0,
          "archived": false,
          "clicked": false,
          "report_reasons": null,
          "author": "mediafiresp",
          "media": null,
          "score": 10,
          "approved_by": null,
          "over_18": false,
          "hidden": false,
          "preview": {
            "images": [
              {
                "source": {
                  "url": "https://i.redditmedia.com/P38dRKXLGjNVhU2Isnwwlj0I5FJhFgareOjwnm_lEWE.jpg?s=6d55d0157d392053f1619bccf9364c71",
                  "width": 200,
                  "height": 200
                },
                "resolutions": [
                  {
                    "url": "https://i.redditmedia.com/P38dRKXLGjNVhU2Isnwwlj0I5FJhFgareOjwnm_lEWE.jpg?fit=crop&amp;crop=faces%2Centropy&amp;arh=2&amp;w=108&amp;s=849c9b4db1f8f3975e191ad655af593b",
                    "width": 108,
                    "height": 108
                  }
                ],
                "variants": {},
                "id": "PAi7QCHtSgEiy8f-GByrzc7WI-OFOp4MW4VwwLGDZnM"
              }
            ]
          },
          "num_comments": 0,
          "thumbnail": "http://b.thumbs.redditmedia.com/DpvgCoNcXHXjrmo9bNcxxP5KLZF7G8bR42tVpfZ7FCA.jpg",
          "subreddit_id": "t5_2qh0s",
          "hide_score": false,
          "edited": false,
          "link_flair_css_class": null,
          "author_flair_css_class": null,
          "downs": 0,
          "secure_media_embed": {},
          "saved": false,
          "removal_reason": null,
          "post_hint": "link",
          "stickied": false,
          "from": null,
          "is_self": false,
          "from_id": null,
          "permalink": "/r/comics/comments/3ilvi0/asterix_obelix_how_fun_were_they_growing_up_here/",
          "name": "t3_3ilvi0",
          "created": 1440717454.0,
          "url": "https://www.userscloud.com/go/d7xs43x1xz37/",
          "author_flair_text": null,
          "quarantine": false,
          "title": "Asterix &amp; Obelix - How fun were they growing up? here are the links if anyone wants to reminiscence.",
          "created_utc": 1440688654.0,
          "distinguished": null,
          "mod_reports": [],
          "visited": false,
          "num_reports": null,
          "ups": 10
        }
      },
      {
        "kind": "t3",
        "data": {
          "domain": "destroyedbyrobots.com",
          "banned_by": null,
          "media_embed": {},
          "subreddit": "comics",
          "selftext_html": null,
          "selftext": "",
          "likes": null,
          "suggested_sort": null,
          "user_reports": [],
          "secure_media": null,
          "link_flair_text": null,
          "id": "3inez4",
          "from_kind": null,
          "gilded": 0,
          "archived": false,
          "clicked": false,
          "report_reasons": null,
          "author": "DestroyedbyRobots",
          "media": null,
          "score": 3,
          "approved_by": null,
          "over_18": false,
          "hidden": false,
          "preview": {
            "images": [
              {
                "source": {
                  "url": "https://i.redditmedia.com/kTCALqsRAAHAfDyFwmzJijkSDxNiOGIoK36SrLvAKo8.jpg?s=9b99186f1742fb24bc99c3edfb26d3cd",
                  "width": 198,
                  "height": 99
                },
                "resolutions": [
                  {
                    "url": "https://i.redditmedia.com/kTCALqsRAAHAfDyFwmzJijkSDxNiOGIoK36SrLvAKo8.jpg?fit=crop&amp;crop=faces%2Centropy&amp;arh=2&amp;w=108&amp;s=0f06b4e0b441b1375d76726da37b1745",
                    "width": 108,
                    "height": 54
                  }
                ],
                "variants": {},
                "id": "caj0OxLDgt-XAi6uN5jKrxtqaikAqsTzil4NgTODFDA"
              }
            ]
          },
          "num_comments": 0,
          "thumbnail": "http://b.thumbs.redditmedia.com/Dq6eGh8Pz4_QHzkqG09moWot0afxDRKATabs7HzFx4I.jpg",
          "subreddit_id": "t5_2qh0s",
          "hide_score": false,
          "edited": false,
          "link_flair_css_class": null,
          "author_flair_css_class": null,
          "downs": 0,
          "secure_media_embed": {},
          "saved": false,
          "removal_reason": null,
          "post_hint": "link",
          "stickied": false,
          "from": null,
          "is_self": false,
          "from_id": null,
          "permalink": "/r/comics/comments/3inez4/it_was_worth_a_shout/",
          "name": "t3_3inez4",
          "created": 1440740549.0,
          "url": "http://destroyedbyrobots.com/2015/08/24/break-and-shout/",
          "author_flair_text": null,
          "quarantine": false,
          "title": "It was worth a shout?",
          "created_utc": 1440711749.0,
          "distinguished": null,
          "mod_reports": [],
          "visited": false,
          "num_reports": null,
          "ups": 3
        }
      },
      {
        "kind": "t3",
        "data": {
          "domain": "paintraincomic.com",
          "banned_by": null,
          "media_embed": {},
          "subreddit": "comics",
          "selftext_html": null,
          "selftext": "",
          "likes": null,
          "suggested_sort": null,
          "user_reports": [],
          "secure_media": null,
          "link_flair_text": null,
          "id": "3im2ds",
          "from_kind": null,
          "gilded": 0,
          "archived": false,
          "clicked": false,
          "report_reasons": null,
          "author": "PainTrainComic",
          "media": null,
          "score": 8,
          "approved_by": null,
          "over_18": false,
          "hidden": false,
          "preview": {
            "images": [
              {
                "source": {
                  "url": "https://i.redditmedia.com/L58_IZX8W7W97Xls-vrvtL6BNZNEgK1QQd6i3bQB4lw.jpg?s=89d0383ce6b07b736bc0747db4f24c5c",
                  "width": 257,
                  "height": 300
                },
                "resolutions": [
                  {
                    "url": "https://i.redditmedia.com/L58_IZX8W7W97Xls-vrvtL6BNZNEgK1QQd6i3bQB4lw.jpg?fit=crop&amp;crop=faces%2Centropy&amp;arh=2&amp;w=108&amp;s=0559b7001c4f0fb1aee2bd0688bdaad1",
                    "width": 108,
                    "height": 126
                  },
                  {
                    "url": "https://i.redditmedia.com/L58_IZX8W7W97Xls-vrvtL6BNZNEgK1QQd6i3bQB4lw.jpg?fit=crop&amp;crop=faces%2Centropy&amp;arh=2&amp;w=216&amp;s=0c49174063d2d1ec023cfbbc84839602",
                    "width": 216,
                    "height": 252
                  }
                ],
                "variants": {},
                "id": "UKZzz-inv1o752JkMykH3_CwBznfjUCqyHuGD7aY2LU"
              }
            ]
          },
          "num_comments": 0,
          "thumbnail": "http://b.thumbs.redditmedia.com/IkLeTjivAwxhbQFkNRExQNgOaF45IS0RePjxckqhuac.jpg",
          "subreddit_id": "t5_2qh0s",
          "hide_score": false,
          "edited": false,
          "link_flair_css_class": null,
          "author_flair_css_class": "artist",
          "downs": 0,
          "secure_media_embed": {},
          "saved": false,
          "removal_reason": null,
          "post_hint": "link",
          "stickied": false,
          "from": null,
          "is_self": false,
          "from_id": null,
          "permalink": "/r/comics/comments/3im2ds/height_hopes/",
          "name": "t3_3im2ds",
          "created": 1440720311.0,
          "url": "http://paintraincomic.com/comic/height-hopes/",
          "author_flair_text": " Pain Train",
          "quarantine": false,
          "title": "Height Hopes",
          "created_utc": 1440691511.0,
          "distinguished": null,
          "mod_reports": [],
          "visited": false,
          "num_reports": null,
          "ups": 8
        }
      },
      {
        "kind": "t3",
        "data": {
          "domain": "i.imgur.com",
          "banned_by": null,
          "media_embed": {},
          "subreddit": "comics",
          "selftext_html": null,
          "selftext": "",
          "likes": null,
          "suggested_sort": null,
          "user_reports": [],
          "secure_media": null,
          "link_flair_text": null,
          "id": "3ikjwj",
          "from_kind": null,
          "gilded": 0,
          "archived": false,
          "clicked": false,
          "report_reasons": null,
          "author": "DoctorWombat",
          "media": null,
          "score": 34,
          "approved_by": null,
          "over_18": false,
          "hidden": false,
          "preview": {
            "images": [
              {
                "source": {
                  "url": "https://i.redditmedia.com/iCY-oIBWLJ9rjvGIUD-bgGebrOC8laYEKTZVx2fmNh4.jpg?s=75aaa506b704bef40f4283b9ab9cbe57",
                  "width": 490,
                  "height": 640
                },
                "resolutions": [
                  {
                    "url": "https://i.redditmedia.com/iCY-oIBWLJ9rjvGIUD-bgGebrOC8laYEKTZVx2fmNh4.jpg?fit=crop&amp;crop=faces%2Centropy&amp;arh=2&amp;w=108&amp;s=928f7ae4431ce714cea2d5c55029d15c",
                    "width": 108,
                    "height": 141
                  },
                  {
                    "url": "https://i.redditmedia.com/iCY-oIBWLJ9rjvGIUD-bgGebrOC8laYEKTZVx2fmNh4.jpg?fit=crop&amp;crop=faces%2Centropy&amp;arh=2&amp;w=216&amp;s=1a212a1d2e8b040b003e65447e720474",
                    "width": 216,
                    "height": 282
                  },
                  {
                    "url": "https://i.redditmedia.com/iCY-oIBWLJ9rjvGIUD-bgGebrOC8laYEKTZVx2fmNh4.jpg?fit=crop&amp;crop=faces%2Centropy&amp;arh=2&amp;w=320&amp;s=9c62062870edf9709ef0501ff0421a27",
                    "width": 320,
                    "height": 417
                  }
                ],
                "variants": {},
                "id": "HzQF0QoRx2DgY6Yyme7fzH402K78z1cWMV0y9XHwGNM"
              }
            ]
          },
          "num_comments": 3,
          "thumbnail": "http://b.thumbs.redditmedia.com/ykJqJogL7RENVTPg4uMMx3RC_icAC77zXxtJLEDUxBw.jpg",
          "subreddit_id": "t5_2qh0s",
          "hide_score": false,
          "edited": false,
          "link_flair_css_class": null,
          "author_flair_css_class": "artist",
          "downs": 0,
          "secure_media_embed": {},
          "saved": false,
          "removal_reason": null,
          "post_hint": "image",
          "stickied": false,
          "from": null,
          "is_self": false,
          "from_id": null,
          "permalink": "/r/comics/comments/3ikjwj/conjuring/",
          "name": "t3_3ikjwj",
          "created": 1440688051.0,
          "url": "http://i.imgur.com/Vds6Yex.png",
          "author_flair_text": "Cheer Up, Emo Kid",
          "quarantine": false,
          "title": "Conjuring",
          "created_utc": 1440659251.0,
          "distinguished": null,
          "mod_reports": [],
          "visited": false,
          "num_reports": null,
          "ups": 34
        }
      },
      {
        "kind": "t3",
        "data": {
          "domain": "couldbeworse-comic.com",
          "banned_by": null,
          "media_embed": {},
          "subreddit": "comics",
          "selftext_html": null,
          "selftext": "",
          "likes": null,
          "suggested_sort": null,
          "user_reports": [],
          "secure_media": null,
          "link_flair_text": null,
          "id": "3inhnk",
          "from_kind": null,
          "gilded": 0,
          "archived": false,
          "clicked": false,
          "report_reasons": null,
          "author": "Watkanjewel",
          "media": null,
          "score": 3,
          "approved_by": null,
          "over_18": false,
          "hidden": false,
          "preview": {
            "images": [
              {
                "source": {
                  "url": "https://i.redditmedia.com/tTEhVr2nnPDcJWFbcqEM6_pLmju5Nrc1e8N275xGcsw.jpg?s=e15572ed28bd062adbbca9eea8974b14",
                  "width": 2000,
                  "height": 690
                },
                "resolutions": [
                  {
                    "url": "https://i.redditmedia.com/tTEhVr2nnPDcJWFbcqEM6_pLmju5Nrc1e8N275xGcsw.jpg?fit=crop&amp;crop=faces%2Centropy&amp;arh=2&amp;w=108&amp;s=e0dbbc40bf7cc442464f6f95a14a3f9e",
                    "width": 108,
                    "height": 37
                  },
                  {
                    "url": "https://i.redditmedia.com/tTEhVr2nnPDcJWFbcqEM6_pLmju5Nrc1e8N275xGcsw.jpg?fit=crop&amp;crop=faces%2Centropy&amp;arh=2&amp;w=216&amp;s=c9e52be7841d0e2366f449e222085f8e",
                    "width": 216,
                    "height": 74
                  },
                  {
                    "url": "https://i.redditmedia.com/tTEhVr2nnPDcJWFbcqEM6_pLmju5Nrc1e8N275xGcsw.jpg?fit=crop&amp;crop=faces%2Centropy&amp;arh=2&amp;w=320&amp;s=5f0628483573f6cc7d91255da09e1f3b",
                    "width": 320,
                    "height": 110
                  },
                  {
                    "url": "https://i.redditmedia.com/tTEhVr2nnPDcJWFbcqEM6_pLmju5Nrc1e8N275xGcsw.jpg?fit=crop&amp;crop=faces%2Centropy&amp;arh=2&amp;w=640&amp;s=a37ac59e0630393d78c531fa16802340",
                    "width": 640,
                    "height": 220
                  },
                  {
                    "url": "https://i.redditmedia.com/tTEhVr2nnPDcJWFbcqEM6_pLmju5Nrc1e8N275xGcsw.jpg?fit=crop&amp;crop=faces%2Centropy&amp;arh=2&amp;w=960&amp;s=22b98bc73212da4b30460c7c1d692d9e",
                    "width": 960,
                    "height": 331
                  },
                  {
                    "url": "https://i.redditmedia.com/tTEhVr2nnPDcJWFbcqEM6_pLmju5Nrc1e8N275xGcsw.jpg?fit=crop&amp;crop=faces%2Centropy&amp;arh=2&amp;w=1080&amp;s=1660b82b202c15c09a87f92d30474180",
                    "width": 1080,
                    "height": 372
                  }
                ],
                "variants": {},
                "id": "BbXJVx9MlawOnAtLjdC5UdA7Htf6VXqWCKnPT6S1dFA"
              }
            ]
          },
          "num_comments": 0,
          "thumbnail": "http://a.thumbs.redditmedia.com/A4ypKhg4NU-DDqW8PQkdFLxKdvCXaNvCWIsXVALhPu4.jpg",
          "subreddit_id": "t5_2qh0s",
          "hide_score": false,
          "edited": false,
          "link_flair_css_class": null,
          "author_flair_css_class": "artist",
          "downs": 0,
          "secure_media_embed": {},
          "saved": false,
          "removal_reason": null,
          "post_hint": "link",
          "stickied": false,
          "from": null,
          "is_self": false,
          "from_id": null,
          "permalink": "/r/comics/comments/3inhnk/unreleased_scenes_from_captain_america_civil_war/",
          "name": "t3_3inhnk",
          "created": 1440741659.0,
          "url": "http://www.couldbeworse-comic.com/386.html",
          "author_flair_text": "Could Be Worse",
          "quarantine": false,
          "title": "Unreleased scenes from Captain America: Civil War",
          "created_utc": 1440712859.0,
          "distinguished": null,
          "mod_reports": [],
          "visited": false,
          "num_reports": null,
          "ups": 3
        }
      },
      {
        "kind": "t3",
        "data": {
          "domain": "i.imgur.com",
          "banned_by": null,
          "media_embed": {},
          "subreddit": "comics",
          "selftext_html": null,
          "selftext": "",
          "likes": null,
          "suggested_sort": null,
          "user_reports": [],
          "secure_media": null,
          "link_flair_text": null,
          "id": "3imwxj",
          "from_kind": null,
          "gilded": 0,
          "archived": false,
          "clicked": false,
          "report_reasons": null,
          "author": "Pullbear",
          "media": null,
          "score": 3,
          "approved_by": null,
          "over_18": false,
          "hidden": false,
          "preview": {
            "images": [
              {
                "source": {
                  "url": "https://i.redditmedia.com/chqOUam3en4u8pct5gfqEKFxloLj00qgQSf1l7viSGY.jpg?s=501a90d031a8d826db58258cf191f6ee",
                  "width": 864,
                  "height": 3276
                },
                "resolutions": [
                  {
                    "url": "https://i.redditmedia.com/chqOUam3en4u8pct5gfqEKFxloLj00qgQSf1l7viSGY.jpg?fit=crop&amp;crop=faces%2Centropy&amp;arh=2&amp;w=108&amp;s=a3292dfee539b56b59f2071b5a0ef11b",
                    "width": 108,
                    "height": 409
                  },
                  {
                    "url": "https://i.redditmedia.com/chqOUam3en4u8pct5gfqEKFxloLj00qgQSf1l7viSGY.jpg?fit=crop&amp;crop=faces%2Centropy&amp;arh=2&amp;w=216&amp;s=43137056fc8a34677f9be795f045d755",
                    "width": 216,
                    "height": 819
                  },
                  {
                    "url": "https://i.redditmedia.com/chqOUam3en4u8pct5gfqEKFxloLj00qgQSf1l7viSGY.jpg?fit=crop&amp;crop=faces%2Centropy&amp;arh=2&amp;w=320&amp;s=48bd340547bfc9b7851e84d74d2550a9",
                    "width": 320,
                    "height": 1213
                  },
                  {
                    "url": "https://i.redditmedia.com/chqOUam3en4u8pct5gfqEKFxloLj00qgQSf1l7viSGY.jpg?fit=crop&amp;crop=faces%2Centropy&amp;arh=2&amp;w=640&amp;s=7f61cb4a112a9085a291e274ee3afee8",
                    "width": 640,
                    "height": 2426
                  }
                ],
                "variants": {},
                "id": "u9Evv6jG2D9_Pc3A6CJyVvhIEyvcN4LonX3vGN6kALU"
              }
            ]
          },
          "num_comments": 0,
          "thumbnail": "http://a.thumbs.redditmedia.com/AobALHx0-EsE4IBfnSEen2KI48B8IQnxrhXSKDfrf30.jpg",
          "subreddit_id": "t5_2qh0s",
          "hide_score": false,
          "edited": false,
          "link_flair_css_class": null,
          "author_flair_css_class": null,
          "downs": 0,
          "secure_media_embed": {},
          "saved": false,
          "removal_reason": null,
          "post_hint": "image",
          "stickied": false,
          "from": null,
          "is_self": false,
          "from_id": null,
          "permalink": "/r/comics/comments/3imwxj/1000_times_to_the_past_oc/",
          "name": "t3_3imwxj",
          "created": 1440732895.0,
          "url": "http://i.imgur.com/sl8rJNX.jpg",
          "author_flair_text": null,
          "quarantine": false,
          "title": "1000 Times To The Past [OC]",
          "created_utc": 1440704095.0,
          "distinguished": null,
          "mod_reports": [],
          "visited": false,
          "num_reports": null,
          "ups": 3
        }
      },
      {
        "kind": "t3",
        "data": {
          "domain": "bonnyjohn.tumblr.com",
          "banned_by": null,
          "media_embed": {},
          "subreddit": "comics",
          "selftext_html": null,
          "selftext": "",
          "likes": null,
          "suggested_sort": null,
          "user_reports": [],
          "secure_media": null,
          "link_flair_text": null,
          "id": "3ijzs0",
          "from_kind": null,
          "gilded": 0,
          "archived": false,
          "clicked": false,
          "report_reasons": null,
          "author": "iamstormborn",
          "media": null,
          "score": 55,
          "approved_by": null,
          "over_18": false,
          "hidden": false,
          "preview": {
            "images": [
              {
                "source": {
                  "url": "https://i.redditmedia.com/j14fJc_eiqrbtQ8moXCpRlxgza0LtUIYDFxBai_QwTk.jpg?s=5ca4aa1a189148415e37f7f049fdb6d7",
                  "width": 500,
                  "height": 750
                },
                "resolutions": [
                  {
                    "url": "https://i.redditmedia.com/j14fJc_eiqrbtQ8moXCpRlxgza0LtUIYDFxBai_QwTk.jpg?fit=crop&amp;crop=faces%2Centropy&amp;arh=2&amp;w=108&amp;s=9b9501f6e4e5d9d48e8be923cae922dc",
                    "width": 108,
                    "height": 162
                  },
                  {
                    "url": "https://i.redditmedia.com/j14fJc_eiqrbtQ8moXCpRlxgza0LtUIYDFxBai_QwTk.jpg?fit=crop&amp;crop=faces%2Centropy&amp;arh=2&amp;w=216&amp;s=c76e53ec51428b7241284e5dafa55e96",
                    "width": 216,
                    "height": 324
                  },
                  {
                    "url": "https://i.redditmedia.com/j14fJc_eiqrbtQ8moXCpRlxgza0LtUIYDFxBai_QwTk.jpg?fit=crop&amp;crop=faces%2Centropy&amp;arh=2&amp;w=320&amp;s=b5e8675a64331846c0c7c2b18bbdbe78",
                    "width": 320,
                    "height": 480
                  }
                ],
                "variants": {},
                "id": "eS6_0-bzGCLTxtQRQptZQQra6TAntXm4EHh11CRaOac"
              }
            ]
          },
          "num_comments": 13,
          "thumbnail": "http://b.thumbs.redditmedia.com/XBKma3qGZxIviGW1Y-xGVwmX_wwBi62EBUtXGs_JDLA.jpg",
          "subreddit_id": "t5_2qh0s",
          "hide_score": false,
          "edited": false,
          "link_flair_css_class": null,
          "author_flair_css_class": null,
          "downs": 0,
          "secure_media_embed": {},
          "saved": false,
          "removal_reason": null,
          "post_hint": "link",
          "stickied": false,
          "from": null,
          "is_self": false,
          "from_id": null,
          "permalink": "/r/comics/comments/3ijzs0/i_drew_up_my_first_comic_with_a_theme_towards/",
          "name": "t3_3ijzs0",
          "created": 1440675794.0,
          "url": "http://bonnyjohn.tumblr.com/post/127674888217/bonny-and-koda-vs-night-night-heres-my-first#notes",
          "author_flair_text": null,
          "quarantine": false,
          "title": "I drew up my first comic, with a theme towards National Dog Day!",
          "created_utc": 1440646994.0,
          "distinguished": null,
          "mod_reports": [],
          "visited": false,
          "num_reports": null,
          "ups": 55
        }
      },
      {
        "kind": "t3",
        "data": {
          "domain": "tubloo.com",
          "banned_by": null,
          "media_embed": {},
          "subreddit": "comics",
          "selftext_html": null,
          "selftext": "",
          "likes": null,
          "suggested_sort": null,
          "user_reports": [],
          "secure_media": null,
          "link_flair_text": null,
          "id": "3io59k",
          "from_kind": null,
          "gilded": 0,
          "archived": false,
          "clicked": false,
          "report_reasons": null,
          "author": "dusique",
          "media": null,
          "score": 0,
          "approved_by": null,
          "over_18": false,
          "hidden": false,
          "preview": {
            "images": [
              {
                "source": {
                  "url": "https://i.redditmedia.com/cNm4C8iaY3kT6siEOhi_J9A-SWDvfOPIsVUKm3jWFfk.jpg?s=690ae5c189d67d1e5bd5b3b40970f226",
                  "width": 225,
                  "height": 225
                },
                "resolutions": [
                  {
                    "url": "https://i.redditmedia.com/cNm4C8iaY3kT6siEOhi_J9A-SWDvfOPIsVUKm3jWFfk.jpg?fit=crop&amp;crop=faces%2Centropy&amp;arh=2&amp;w=108&amp;s=87b89c966bc4dea56b96485a945512c9",
                    "width": 108,
                    "height": 108
                  },
                  {
                    "url": "https://i.redditmedia.com/cNm4C8iaY3kT6siEOhi_J9A-SWDvfOPIsVUKm3jWFfk.jpg?fit=crop&amp;crop=faces%2Centropy&amp;arh=2&amp;w=216&amp;s=8a9dab3fb6b37ee3df8adfaec8080ae1",
                    "width": 216,
                    "height": 216
                  }
                ],
                "variants": {},
                "id": "K5nuojx2pehrH_nq18OzE78RgVzWO0z4S19eWNfpFN8"
              }
            ]
          },
          "num_comments": 1,
          "thumbnail": "http://a.thumbs.redditmedia.com/V6X0pFzLvsT7Ihz9Ccvtg-ntCkZMmP-3dWOsr3ZiJn0.jpg",
          "subreddit_id": "t5_2qh0s",
          "hide_score": true,
          "edited": false,
          "link_flair_css_class": null,
          "author_flair_css_class": "artist",
          "downs": 0,
          "secure_media_embed": {},
          "saved": false,
          "removal_reason": null,
          "post_hint": "link",
          "stickied": false,
          "from": null,
          "is_self": false,
          "from_id": null,
          "permalink": "/r/comics/comments/3io59k/oc_project_z_ep01_background_music_included_watch/",
          "name": "t3_3io59k",
          "created": 1440752991.0,
          "url": "http://www.tubloo.com/10203",
          "author_flair_text": "dusique",
          "quarantine": false,
          "title": "[OC] Project Z ep.01 (background music included - watch out!)",
          "created_utc": 1440724191.0,
          "distinguished": null,
          "mod_reports": [],
          "visited": false,
          "num_reports": null,
          "ups": 0
        }
      },
      {
        "kind": "t3",
        "data": {
          "domain": "i.imgur.com",
          "banned_by": null,
          "media_embed": {},
          "subreddit": "comics",
          "selftext_html": null,
          "selftext": "",
          "likes": null,
          "suggested_sort": null,
          "user_reports": [],
          "secure_media": null,
          "link_flair_text": null,
          "id": "3iggf0",
          "from_kind": null,
          "gilded": 0,
          "archived": false,
          "clicked": false,
          "report_reasons": null,
          "author": "shenanigansen",
          "media": null,
          "score": 890,
          "approved_by": null,
          "over_18": false,
          "hidden": false,
          "preview": {
            "images": [
              {
                "source": {
                  "url": "https://i.redditmedia.com/Td-bKoRq1xVUvXP8Q0dcZ5vPl5gqygSoYq4pwOwhZN8.jpg?s=328bfe10e334b3056e2f3061736b58fc",
                  "width": 800,
                  "height": 6744
                },
                "resolutions": [
                  {
                    "url": "https://i.redditmedia.com/Td-bKoRq1xVUvXP8Q0dcZ5vPl5gqygSoYq4pwOwhZN8.jpg?fit=crop&amp;crop=faces%2Centropy&amp;arh=2&amp;w=108&amp;s=6020ad682c99e81ab347c87e5e438022",
                    "width": 108,
                    "height": 910
                  },
                  {
                    "url": "https://i.redditmedia.com/Td-bKoRq1xVUvXP8Q0dcZ5vPl5gqygSoYq4pwOwhZN8.jpg?fit=crop&amp;crop=faces%2Centropy&amp;arh=2&amp;w=216&amp;s=0531fcc981350e43e1e6c9a5e24b6d50",
                    "width": 216,
                    "height": 1820
                  },
                  {
                    "url": "https://i.redditmedia.com/Td-bKoRq1xVUvXP8Q0dcZ5vPl5gqygSoYq4pwOwhZN8.jpg?fit=crop&amp;crop=faces%2Centropy&amp;arh=2&amp;w=320&amp;s=d9cac45cb94919a52a8b97092aa38972",
                    "width": 320,
                    "height": 2697
                  },
                  {
                    "url": "https://i.redditmedia.com/Td-bKoRq1xVUvXP8Q0dcZ5vPl5gqygSoYq4pwOwhZN8.jpg?fit=crop&amp;crop=faces%2Centropy&amp;arh=2&amp;w=640&amp;s=99ef7401e0e4df7e1787c5ce32772d03",
                    "width": 640,
                    "height": 5395
                  }
                ],
                "variants": {},
                "id": "xZG6lXi5sa6pavNPB68yMOTAYi5-O0dD_slRcQ8pZ1s"
              }
            ]
          },
          "num_comments": 27,
          "thumbnail": "http://b.thumbs.redditmedia.com/dil0MEW4d8YhGvfx0YFRZDJXLWNSsXQ_aKJa1LWbsBg.jpg",
          "subreddit_id": "t5_2qh0s",
          "hide_score": false,
          "edited": false,
          "link_flair_css_class": null,
          "author_flair_css_class": "artist",
          "downs": 0,
          "secure_media_embed": {},
          "saved": false,
          "removal_reason": null,
          "post_hint": "image",
          "stickied": false,
          "from": null,
          "is_self": false,
          "from_id": null,
          "permalink": "/r/comics/comments/3iggf0/water_country_water_country/",
          "name": "t3_3iggf0",
          "created": 1440593979.0,
          "url": "http://i.imgur.com/IqTD3vU.png",
          "author_flair_text": "Owl Turd",
          "quarantine": false,
          "title": "WATER COUNTRY, WATER COUNTRY",
          "created_utc": 1440590379.0,
          "distinguished": null,
          "mod_reports": [],
          "visited": false,
          "num_reports": null,
          "ups": 890
        }
      },
      {
        "kind": "t3",
        "data": {
          "domain": "blog.squareplanetcomics.com",
          "banned_by": null,
          "media_embed": {},
          "subreddit": "comics",
          "selftext_html": null,
          "selftext": "",
          "likes": null,
          "suggested_sort": null,
          "user_reports": [],
          "secure_media": null,
          "link_flair_text": null,
          "id": "3in8ku",
          "from_kind": null,
          "gilded": 0,
          "archived": false,
          "clicked": false,
          "report_reasons": null,
          "author": "Blastosaurus",
          "media": null,
          "score": 2,
          "approved_by": null,
          "over_18": false,
          "hidden": false,
          "preview": {
            "images": [
              {
                "source": {
                  "url": "https://i.redditmedia.com/F6AGihc6sjMmnVLm-XWIe0jcP2vPZpBwjOqH2PhZX-c.jpg?s=56a677929f9af56fa137ae07c36cfd15",
                  "width": 200,
                  "height": 200
                },
                "resolutions": [
                  {
                    "url": "https://i.redditmedia.com/F6AGihc6sjMmnVLm-XWIe0jcP2vPZpBwjOqH2PhZX-c.jpg?fit=crop&amp;crop=faces%2Centropy&amp;arh=2&amp;w=108&amp;s=482dd3c6232f59884e434a498faa2cbd",
                    "width": 108,
                    "height": 108
                  }
                ],
                "variants": {},
                "id": "sAYY86zgdT-GUuuQxQ55XhcVr4wy0uMIajd_UOBdg3Y"
              }
            ]
          },
          "num_comments": 0,
          "thumbnail": "http://b.thumbs.redditmedia.com/6E0YXUncXhFZE-HgC8IH7COjePvS20nr4P30WrcpyiU.jpg",
          "subreddit_id": "t5_2qh0s",
          "hide_score": false,
          "edited": false,
          "link_flair_css_class": null,
          "author_flair_css_class": null,
          "downs": 0,
          "secure_media_embed": {},
          "saved": false,
          "removal_reason": null,
          "post_hint": "link",
          "stickied": false,
          "from": null,
          "is_self": false,
          "from_id": null,
          "permalink": "/r/comics/comments/3in8ku/the_case_of_the_spirited_septuagenarian/",
          "name": "t3_3in8ku",
          "created": 1440737772.0,
          "url": "http://blog.squareplanetcomics.com/43-the-case-of-the-spirited-septuagenarian/",
          "author_flair_text": null,
          "quarantine": false,
          "title": "The Case of the Spirited Septuagenarian",
          "created_utc": 1440708972.0,
          "distinguished": null,
          "mod_reports": [],
          "visited": false,
          "num_reports": null,
          "ups": 2
        }
      },
      {
        "kind": "t3",
        "data": {
          "domain": "piecomic.tumblr.com",
          "banned_by": null,
          "media_embed": {},
          "subreddit": "comics",
          "selftext_html": null,
          "selftext": "",
          "likes": null,
          "suggested_sort": null,
          "user_reports": [],
          "secure_media": null,
          "link_flair_text": null,
          "id": "3ihnx3",
          "from_kind": null,
          "gilded": 0,
          "archived": false,
          "clicked": false,
          "report_reasons": null,
          "author": "dredgeups",
          "media": null,
          "score": 310,
          "approved_by": null,
          "over_18": false,
          "hidden": false,
          "preview": {
            "images": [
              {
                "source": {
                  "url": "https://i.redditmedia.com/G-Af3uftaIjLZNcg48dFb5tvBkIhgi3BWNyryXYra8U.jpg?s=3a63fca9d41d81b49694bfbb21168a16",
                  "width": 500,
                  "height": 671
                },
                "resolutions": [
                  {
                    "url": "https://i.redditmedia.com/G-Af3uftaIjLZNcg48dFb5tvBkIhgi3BWNyryXYra8U.jpg?fit=crop&amp;crop=faces%2Centropy&amp;arh=2&amp;w=108&amp;s=c96a680eaf44ffddca8cefbb62a8e8a2",
                    "width": 108,
                    "height": 144
                  },
                  {
                    "url": "https://i.redditmedia.com/G-Af3uftaIjLZNcg48dFb5tvBkIhgi3BWNyryXYra8U.jpg?fit=crop&amp;crop=faces%2Centropy&amp;arh=2&amp;w=216&amp;s=bee67893665b33673055258eaf64654f",
                    "width": 216,
                    "height": 289
                  },
                  {
                    "url": "https://i.redditmedia.com/G-Af3uftaIjLZNcg48dFb5tvBkIhgi3BWNyryXYra8U.jpg?fit=crop&amp;crop=faces%2Centropy&amp;arh=2&amp;w=320&amp;s=bd2d09428aff423e3cce42a354bfa847",
                    "width": 320,
                    "height": 429
                  }
                ],
                "variants": {},
                "id": "GGnJEWTKEHVRdLE30cQV_ZLQFDp7qIS9-hcqPVcP3ko"
              }
            ]
          },
          "num_comments": 9,
          "thumbnail": "http://a.thumbs.redditmedia.com/NxfDyiIN5wOOyO0JJA7nIXCfZ8Hy1SnFm7CeccKlmR0.jpg",
          "subreddit_id": "t5_2qh0s",
          "hide_score": false,
          "edited": false,
          "link_flair_css_class": null,
          "author_flair_css_class": "artist",
          "downs": 0,
          "secure_media_embed": {},
          "saved": false,
          "removal_reason": null,
          "post_hint": "link",
          "stickied": false,
          "from": null,
          "is_self": false,
          "from_id": null,
          "permalink": "/r/comics/comments/3ihnx3/where_do_babies_come_from/",
          "name": "t3_3ihnx3",
          "created": 1440613740.0,
          "url": "http://piecomic.tumblr.com/post/127579945027",
          "author_flair_text": "Pie Comic",
          "quarantine": false,
          "title": "Where Do Babies Come From?",
          "created_utc": 1440610140.0,
          "distinguished": null,
          "mod_reports": [],
          "visited": false,
          "num_reports": null,
          "ups": 310
        }
      },
      {
        "kind": "t3",
        "data": {
          "domain": "steveogden.com",
          "banned_by": null,
          "media_embed": {},
          "subreddit": "comics",
          "selftext_html": null,
          "selftext": "",
          "likes": null,
          "suggested_sort": null,
          "user_reports": [],
          "secure_media": null,
          "link_flair_text": null,
          "id": "3ilag4",
          "from_kind": null,
          "gilded": 0,
          "archived": false,
          "clicked": false,
          "report_reasons": null,
          "author": "SimonTrip",
          "media": null,
          "score": 10,
          "approved_by": null,
          "over_18": false,
          "hidden": false,
          "preview": {
            "images": [
              {
                "source": {
                  "url": "https://i.redditmedia.com/BRIA27H0l0OH3mpGVPYR7RDqYPjmVFD2quqOZ21RAYs.jpg?s=6846cbf2a6f1753957df49c40a5466c8",
                  "width": 980,
                  "height": 344
                },
                "resolutions": [
                  {
                    "url": "https://i.redditmedia.com/BRIA27H0l0OH3mpGVPYR7RDqYPjmVFD2quqOZ21RAYs.jpg?fit=crop&amp;crop=faces%2Centropy&amp;arh=2&amp;w=108&amp;s=20983eb78798d96fb179c0324bcb46d6",
                    "width": 108,
                    "height": 37
                  },
                  {
                    "url": "https://i.redditmedia.com/BRIA27H0l0OH3mpGVPYR7RDqYPjmVFD2quqOZ21RAYs.jpg?fit=crop&amp;crop=faces%2Centropy&amp;arh=2&amp;w=216&amp;s=45d210996c35c25733bf4292863e630d",
                    "width": 216,
                    "height": 75
                  },
                  {
                    "url": "https://i.redditmedia.com/BRIA27H0l0OH3mpGVPYR7RDqYPjmVFD2quqOZ21RAYs.jpg?fit=crop&amp;crop=faces%2Centropy&amp;arh=2&amp;w=320&amp;s=f5a92b8f3d387b51863add17c2a827eb",
                    "width": 320,
                    "height": 112
                  },
                  {
                    "url": "https://i.redditmedia.com/BRIA27H0l0OH3mpGVPYR7RDqYPjmVFD2quqOZ21RAYs.jpg?fit=crop&amp;crop=faces%2Centropy&amp;arh=2&amp;w=640&amp;s=8144440d3bc52bf44cbceeb263990e12",
                    "width": 640,
                    "height": 224
                  },
                  {
                    "url": "https://i.redditmedia.com/BRIA27H0l0OH3mpGVPYR7RDqYPjmVFD2quqOZ21RAYs.jpg?fit=crop&amp;crop=faces%2Centropy&amp;arh=2&amp;w=960&amp;s=dfd5d5ec8c96c37518c73a38bdd844d2",
                    "width": 960,
                    "height": 336
                  }
                ],
                "variants": {},
                "id": "SatlzF-peidpwiLs6RpoghudpaYXYq5iZD4B14dIssE"
              }
            ]
          },
          "num_comments": 4,
          "thumbnail": "http://b.thumbs.redditmedia.com/-Ctwb3yM39vduykgtOuKQ_oDEyX04XKiNf3FnvJKKMM.jpg",
          "subreddit_id": "t5_2qh0s",
          "hide_score": false,
          "edited": false,
          "link_flair_css_class": null,
          "author_flair_css_class": null,
          "downs": 0,
          "secure_media_embed": {},
          "saved": false,
          "removal_reason": null,
          "post_hint": "link",
          "stickied": false,
          "from": null,
          "is_self": false,
          "from_id": null,
          "permalink": "/r/comics/comments/3ilag4/the_decline_of_the_human_race_will_be_televised/",
          "name": "t3_3ilag4",
          "created": 1440707398.0,
          "url": "http://steveogden.com/magnifico/comic/97-world-news/",
          "author_flair_text": null,
          "quarantine": false,
          "title": "The decline of the human race will be televised",
          "created_utc": 1440678598.0,
          "distinguished": null,
          "mod_reports": [],
          "visited": false,
          "num_reports": null,
          "ups": 10
        }
      },
      {
        "kind": "t3",
        "data": {
          "domain": "epicstream.com",
          "banned_by": null,
          "media_embed": {},
          "subreddit": "comics",
          "selftext_html": null,
          "selftext": "",
          "likes": null,
          "suggested_sort": null,
          "user_reports": [],
          "secure_media": null,
          "link_flair_text": null,
          "id": "3ilpeu",
          "from_kind": null,
          "gilded": 0,
          "archived": false,
          "clicked": false,
          "report_reasons": null,
          "author": "cyborgian",
          "media": null,
          "score": 6,
          "approved_by": null,
          "over_18": false,
          "hidden": false,
          "preview": {
            "images": [
              {
                "source": {
                  "url": "https://i.redditmedia.com/L5PoFXUkbK0_3gtg4oSWRLVnKdJTLRkoPH99n_GPF9o.jpg?s=d819948909f9b59537fc8d8e8f0edf66",
                  "width": 640,
                  "height": 335
                },
                "resolutions": [
                  {
                    "url": "https://i.redditmedia.com/L5PoFXUkbK0_3gtg4oSWRLVnKdJTLRkoPH99n_GPF9o.jpg?fit=crop&amp;crop=faces%2Centropy&amp;arh=2&amp;w=108&amp;s=3241f145c6ae446c64b69b1d324e226d",
                    "width": 108,
                    "height": 56
                  },
                  {
                    "url": "https://i.redditmedia.com/L5PoFXUkbK0_3gtg4oSWRLVnKdJTLRkoPH99n_GPF9o.jpg?fit=crop&amp;crop=faces%2Centropy&amp;arh=2&amp;w=216&amp;s=1f17e2128370cbef403d08d9a544fe2a",
                    "width": 216,
                    "height": 113
                  },
                  {
                    "url": "https://i.redditmedia.com/L5PoFXUkbK0_3gtg4oSWRLVnKdJTLRkoPH99n_GPF9o.jpg?fit=crop&amp;crop=faces%2Centropy&amp;arh=2&amp;w=320&amp;s=288b3ca6bea9072f03b63d47a83d015c",
                    "width": 320,
                    "height": 167
                  },
                  {
                    "url": "https://i.redditmedia.com/L5PoFXUkbK0_3gtg4oSWRLVnKdJTLRkoPH99n_GPF9o.jpg?fit=crop&amp;crop=faces%2Centropy&amp;arh=2&amp;w=640&amp;s=de94b17c6bd6c9736adedf1fe07a4ee6",
                    "width": 640,
                    "height": 335
                  }
                ],
                "variants": {},
                "id": "yXT8__TAs71usXwtwXRfaIM92lmCP03P8UDJKnUjUjU"
              }
            ]
          },
          "num_comments": 1,
          "thumbnail": "http://b.thumbs.redditmedia.com/jcHeJ3Vgu_Zj2-KEnoW7LPpaAVGlPfP38ukXEG13Dfo.jpg",
          "subreddit_id": "t5_2qh0s",
          "hide_score": false,
          "edited": false,
          "link_flair_css_class": null,
          "author_flair_css_class": null,
          "downs": 0,
          "secure_media_embed": {},
          "saved": false,
          "removal_reason": null,
          "post_hint": "link",
          "stickied": false,
          "from": null,
          "is_self": false,
          "from_id": null,
          "permalink": "/r/comics/comments/3ilpeu/what_does_a_tetrahedral_astromech_droid_roll/",
          "name": "t3_3ilpeu",
          "created": 1440714779.0,
          "url": "http://epicstream.com/comics/What-Does-a-Tetrahedral-Astromech-Droid-Roll",
          "author_flair_text": null,
          "quarantine": false,
          "title": "What Does a Tetrahedral Astromech Droid Roll?",
          "created_utc": 1440685979.0,
          "distinguished": null,
          "mod_reports": [],
          "visited": false,
          "num_reports": null,
          "ups": 6
        }
      },
      {
        "kind": "t3",
        "data": {
          "domain": "rubbateets.com",
          "banned_by": null,
          "media_embed": {},
          "subreddit": "comics",
          "selftext_html": null,
          "selftext": "",
          "likes": null,
          "suggested_sort": null,
          "user_reports": [],
          "secure_media": null,
          "link_flair_text": null,
          "id": "3in4k8",
          "from_kind": null,
          "gilded": 0,
          "archived": false,
          "clicked": false,
          "report_reasons": null,
          "author": "madmonkeymonk1978",
          "media": null,
          "score": 2,
          "approved_by": null,
          "over_18": false,
          "hidden": false,
          "preview": {
            "images": [
              {
                "source": {
                  "url": "https://i.redditmedia.com/9h6ygU5cL2eu-SPFpCiZVhyA90hTTIrGXR1jrVLyL0U.jpg?s=70782dac99210bee2e16334d427c5720",
                  "width": 1024,
                  "height": 355
                },
                "resolutions": [
                  {
                    "url": "https://i.redditmedia.com/9h6ygU5cL2eu-SPFpCiZVhyA90hTTIrGXR1jrVLyL0U.jpg?fit=crop&amp;crop=faces%2Centropy&amp;arh=2&amp;w=108&amp;s=7aae99eebe5a9347c7d9b92d1847456c",
                    "width": 108,
                    "height": 37
                  },
                  {
                    "url": "https://i.redditmedia.com/9h6ygU5cL2eu-SPFpCiZVhyA90hTTIrGXR1jrVLyL0U.jpg?fit=crop&amp;crop=faces%2Centropy&amp;arh=2&amp;w=216&amp;s=61fab62df97eeaa07f60c7f9329cf50f",
                    "width": 216,
                    "height": 74
                  },
                  {
                    "url": "https://i.redditmedia.com/9h6ygU5cL2eu-SPFpCiZVhyA90hTTIrGXR1jrVLyL0U.jpg?fit=crop&amp;crop=faces%2Centropy&amp;arh=2&amp;w=320&amp;s=ac5667226a52a3b346adeeae9dcda754",
                    "width": 320,
                    "height": 110
                  },
                  {
                    "url": "https://i.redditmedia.com/9h6ygU5cL2eu-SPFpCiZVhyA90hTTIrGXR1jrVLyL0U.jpg?fit=crop&amp;crop=faces%2Centropy&amp;arh=2&amp;w=640&amp;s=b29d887084f3e0ceedcacbc5dd07f901",
                    "width": 640,
                    "height": 221
                  },
                  {
                    "url": "https://i.redditmedia.com/9h6ygU5cL2eu-SPFpCiZVhyA90hTTIrGXR1jrVLyL0U.jpg?fit=crop&amp;crop=faces%2Centropy&amp;arh=2&amp;w=960&amp;s=d3d48db3ebfd0fc27caef6d613174af7",
                    "width": 960,
                    "height": 332
                  }
                ],
                "variants": {},
                "id": "ZgoAubd8cudo6pM8KkznSN70XYx0zv7nOxlaLo30qAU"
              }
            ]
          },
          "num_comments": 0,
          "thumbnail": "http://b.thumbs.redditmedia.com/tuPHqMWfc1Z60spQprWog8SZ9I6ZQxhgTexsXQdnwNw.jpg",
          "subreddit_id": "t5_2qh0s",
          "hide_score": false,
          "edited": false,
          "link_flair_css_class": null,
          "author_flair_css_class": "artist",
          "downs": 0,
          "secure_media_embed": {},
          "saved": false,
          "removal_reason": null,
          "post_hint": "link",
          "stickied": false,
          "from": null,
          "is_self": false,
          "from_id": null,
          "permalink": "/r/comics/comments/3in4k8/math_sucks_14/",
          "name": "t3_3in4k8",
          "created": 1440736125.0,
          "url": "http://www.rubbateets.com/comic/math-sucks-14/",
          "author_flair_text": "Pickletits",
          "quarantine": false,
          "title": "Math Sucks 14",
          "created_utc": 1440707325.0,
          "distinguished": null,
          "mod_reports": [],
          "visited": false,
          "num_reports": null,
          "ups": 2
        }
      },
      {
        "kind": "t3",
        "data": {
          "domain": "theycantalk.com",
          "banned_by": null,
          "media_embed": {},
          "subreddit": "comics",
          "selftext_html": null,
          "selftext": "",
          "likes": null,
          "suggested_sort": null,
          "user_reports": [],
          "secure_media": null,
          "link_flair_text": null,
          "id": "3illy9",
          "from_kind": null,
          "gilded": 0,
          "archived": false,
          "clicked": false,
          "report_reasons": null,
          "author": "theycantalk",
          "media": null,
          "score": 7,
          "approved_by": null,
          "over_18": false,
          "hidden": false,
          "preview": {
            "images": [
              {
                "source": {
                  "url": "https://i.redditmedia.com/ykRwKIwQO5iBRyUBf1yWrZLMRGXW0Qbsjrb1_25WE9E.jpg?s=7374cdcb62fc4ff80f59d2fc97fe605a",
                  "width": 600,
                  "height": 614
                },
                "resolutions": [
                  {
                    "url": "https://i.redditmedia.com/ykRwKIwQO5iBRyUBf1yWrZLMRGXW0Qbsjrb1_25WE9E.jpg?fit=crop&amp;crop=faces%2Centropy&amp;arh=2&amp;w=108&amp;s=b6370baa4c407af2aa6bf7253b2ce837",
                    "width": 108,
                    "height": 110
                  },
                  {
                    "url": "https://i.redditmedia.com/ykRwKIwQO5iBRyUBf1yWrZLMRGXW0Qbsjrb1_25WE9E.jpg?fit=crop&amp;crop=faces%2Centropy&amp;arh=2&amp;w=216&amp;s=ce246e47874c7f06c4b30423bb912c71",
                    "width": 216,
                    "height": 221
                  },
                  {
                    "url": "https://i.redditmedia.com/ykRwKIwQO5iBRyUBf1yWrZLMRGXW0Qbsjrb1_25WE9E.jpg?fit=crop&amp;crop=faces%2Centropy&amp;arh=2&amp;w=320&amp;s=96776f2b2adaf9c0669239e8622d5b26",
                    "width": 320,
                    "height": 327
                  }
                ],
                "variants": {},
                "id": "THWC52Mr9m7LcSDH0BqR3DELjYRZeU9EzLy9Im2Y1AA"
              }
            ]
          },
          "num_comments": 0,
          "thumbnail": "http://b.thumbs.redditmedia.com/WSt9TeUcwHniRio2QrPcLqkvKkgP_GXzuOPIJbEz1xU.jpg",
          "subreddit_id": "t5_2qh0s",
          "hide_score": false,
          "edited": false,
          "link_flair_css_class": null,
          "author_flair_css_class": "artist",
          "downs": 0,
          "secure_media_embed": {},
          "saved": false,
          "removal_reason": null,
          "post_hint": "link",
          "stickied": false,
          "from": null,
          "is_self": false,
          "from_id": null,
          "permalink": "/r/comics/comments/3illy9/are_we_there_yet/",
          "name": "t3_3illy9",
          "created": 1440713227.0,
          "url": "http://theycantalk.com/post/127709662680/are-we-there-yet",
          "author_flair_text": "They can talk.",
          "quarantine": false,
          "title": "are we there yet?",
          "created_utc": 1440684427.0,
          "distinguished": null,
          "mod_reports": [],
          "visited": false,
          "num_reports": null,
          "ups": 7
        }
      },
      {
        "kind": "t3",
        "data": {
          "domain": "webtoons.com",
          "banned_by": null,
          "media_embed": {},
          "subreddit": "comics",
          "selftext_html": null,
          "selftext": "",
          "likes": null,
          "suggested_sort": null,
          "user_reports": [],
          "secure_media": null,
          "link_flair_text": null,
          "id": "3invh7",
          "from_kind": null,
          "gilded": 0,
          "archived": false,
          "clicked": false,
          "report_reasons": null,
          "author": "Justin3613",
          "media": null,
          "score": 1,
          "approved_by": null,
          "over_18": false,
          "hidden": false,
          "preview": {
            "images": [
              {
                "source": {
                  "url": "https://i.redditmedia.com/e4kz3rQSndFnjySkuWz-XTosjIJWoXX0SFkxuuG0ARQ.jpg?s=8c592ebc8dd6542ab9049043572990a7",
                  "width": 436,
                  "height": 436
                },
                "resolutions": [
                  {
                    "url": "https://i.redditmedia.com/e4kz3rQSndFnjySkuWz-XTosjIJWoXX0SFkxuuG0ARQ.jpg?fit=crop&amp;crop=faces%2Centropy&amp;arh=2&amp;w=108&amp;s=ebdc424691c46ff8c5f35dbe71c076f7",
                    "width": 108,
                    "height": 108
                  },
                  {
                    "url": "https://i.redditmedia.com/e4kz3rQSndFnjySkuWz-XTosjIJWoXX0SFkxuuG0ARQ.jpg?fit=crop&amp;crop=faces%2Centropy&amp;arh=2&amp;w=216&amp;s=fc24e622756ead808020a37723debc65",
                    "width": 216,
                    "height": 216
                  },
                  {
                    "url": "https://i.redditmedia.com/e4kz3rQSndFnjySkuWz-XTosjIJWoXX0SFkxuuG0ARQ.jpg?fit=crop&amp;crop=faces%2Centropy&amp;arh=2&amp;w=320&amp;s=4f4379d3158d6b847cf52afbcf757053",
                    "width": 320,
                    "height": 320
                  }
                ],
                "variants": {},
                "id": "8Tw9sTeCimrDAyrt5FnW9SR40OFo7UmgMaFXteahicY"
              }
            ]
          },
          "num_comments": 0,
          "thumbnail": "http://a.thumbs.redditmedia.com/1DvxJ8FuyJ9cL5rozxmJG1sO4AO9BYOCHWihvk-CSL8.jpg",
          "subreddit_id": "t5_2qh0s",
          "hide_score": false,
          "edited": false,
          "link_flair_css_class": null,
          "author_flair_css_class": null,
          "downs": 0,
          "secure_media_embed": {},
          "saved": false,
          "removal_reason": null,
          "post_hint": "link",
          "stickied": false,
          "from": null,
          "is_self": false,
          "from_id": null,
          "permalink": "/r/comics/comments/3invh7/that_socially_awkward_guy_comic_series/",
          "name": "t3_3invh7",
          "created": 1440748155.0,
          "url": "http://www.webtoons.com/en/challenge/that-socially-awkard-guy/list?title_no=9153",
          "author_flair_text": null,
          "quarantine": false,
          "title": "That Socially Awkward Guy (Comic Series)",
          "created_utc": 1440719355.0,
          "distinguished": null,
          "mod_reports": [],
          "visited": false,
          "num_reports": null,
          "ups": 1
        }
      },
      {
        "kind": "t3",
        "data": {
          "domain": "i.imgur.com",
          "banned_by": null,
          "media_embed": {},
          "subreddit": "comics",
          "selftext_html": null,
          "selftext": "",
          "likes": null,
          "suggested_sort": null,
          "user_reports": [],
          "secure_media": null,
          "link_flair_text": null,
          "id": "3ikw6v",
          "from_kind": null,
          "gilded": 0,
          "archived": false,
          "clicked": false,
          "report_reasons": null,
          "author": "ubertool",
          "media": null,
          "score": 15,
          "approved_by": null,
          "over_18": false,
          "hidden": false,
          "preview": {
            "images": [
              {
                "source": {
                  "url": "https://i.redditmedia.com/uwNmQwEERxEjM6GFVSD41YAGc1L0Up9rafo-h7x9y0E.jpg?s=5e3f4c1eb5e315b4377799a854521369",
                  "width": 1488,
                  "height": 2105
                },
                "resolutions": [
                  {
                    "url": "https://i.redditmedia.com/uwNmQwEERxEjM6GFVSD41YAGc1L0Up9rafo-h7x9y0E.jpg?fit=crop&amp;crop=faces%2Centropy&amp;arh=2&amp;w=108&amp;s=d4d4d87eabbafab57f1be7969f6ebef2",
                    "width": 108,
                    "height": 152
                  },
                  {
                    "url": "https://i.redditmedia.com/uwNmQwEERxEjM6GFVSD41YAGc1L0Up9rafo-h7x9y0E.jpg?fit=crop&amp;crop=faces%2Centropy&amp;arh=2&amp;w=216&amp;s=5bd6046776a3d6807a4e626ca4bd9fd5",
                    "width": 216,
                    "height": 305
                  },
                  {
                    "url": "https://i.redditmedia.com/uwNmQwEERxEjM6GFVSD41YAGc1L0Up9rafo-h7x9y0E.jpg?fit=crop&amp;crop=faces%2Centropy&amp;arh=2&amp;w=320&amp;s=d5d3ecb945b84db740d233a9f9648ee3",
                    "width": 320,
                    "height": 452
                  },
                  {
                    "url": "https://i.redditmedia.com/uwNmQwEERxEjM6GFVSD41YAGc1L0Up9rafo-h7x9y0E.jpg?fit=crop&amp;crop=faces%2Centropy&amp;arh=2&amp;w=640&amp;s=dfebeea78a40c6f63233310731bebf01",
                    "width": 640,
                    "height": 905
                  },
                  {
                    "url": "https://i.redditmedia.com/uwNmQwEERxEjM6GFVSD41YAGc1L0Up9rafo-h7x9y0E.jpg?fit=crop&amp;crop=faces%2Centropy&amp;arh=2&amp;w=960&amp;s=082840eb9b06c169358723e742e17a1d",
                    "width": 960,
                    "height": 1358
                  },
                  {
                    "url": "https://i.redditmedia.com/uwNmQwEERxEjM6GFVSD41YAGc1L0Up9rafo-h7x9y0E.jpg?fit=crop&amp;crop=faces%2Centropy&amp;arh=2&amp;w=1080&amp;s=934408cbb57c356778c28e1948a1074b",
                    "width": 1080,
                    "height": 1527
                  }
                ],
                "variants": {},
                "id": "91NPnjS3een8o-_HS0jcTD9OhbdfPyZjcdKcGUgN7ts"
              }
            ]
          },
          "num_comments": 3,
          "thumbnail": "http://b.thumbs.redditmedia.com/PisqQ_y3dkBS5ii9OFnCBFT1EyzgkNePBtcXMfE0ris.jpg",
          "subreddit_id": "t5_2qh0s",
          "hide_score": false,
          "edited": false,
          "link_flair_css_class": null,
          "author_flair_css_class": "artist",
          "downs": 0,
          "secure_media_embed": {},
          "saved": false,
          "removal_reason": null,
          "post_hint": "image",
          "stickied": false,
          "from": null,
          "is_self": false,
          "from_id": null,
          "permalink": "/r/comics/comments/3ikw6v/spicy_chicken/",
          "name": "t3_3ikw6v",
          "created": 1440672388.0,
          "url": "http://i.imgur.com/LSSl18z.jpg",
          "author_flair_text": "\u00fcbertool",
          "quarantine": false,
          "title": "Spicy Chicken",
          "created_utc": 1440668788.0,
          "distinguished": null,
          "mod_reports": [],
          "visited": false,
          "num_reports": null,
          "ups": 15
        }
      },
      {
        "kind": "t3",
        "data": {
          "domain": "lolnein.com",
          "banned_by": null,
          "media_embed": {},
          "subreddit": "comics",
          "selftext_html": null,
          "selftext": "",
          "likes": null,
          "suggested_sort": null,
          "user_reports": [],
          "secure_media": null,
          "link_flair_text": null,
          "id": "3iled7",
          "from_kind": null,
          "gilded": 0,
          "archived": false,
          "clicked": false,
          "report_reasons": null,
          "author": "lolnein",
          "media": null,
          "score": 7,
          "approved_by": null,
          "over_18": false,
          "hidden": false,
          "preview": {
            "images": [
              {
                "source": {
                  "url": "https://i.redditmedia.com/C0edo3GQfqJC44uCCdDXoJxmXvEmAU9sM203mc3SVlE.jpg?s=bd7f38d884974d2aa171d2c93d6e6e6c",
                  "width": 798,
                  "height": 1140
                },
                "resolutions": [
                  {
                    "url": "https://i.redditmedia.com/C0edo3GQfqJC44uCCdDXoJxmXvEmAU9sM203mc3SVlE.jpg?fit=crop&amp;crop=faces%2Centropy&amp;arh=2&amp;w=108&amp;s=2d20ee29d0673e814ded0ea449af2905",
                    "width": 108,
                    "height": 154
                  },
                  {
                    "url": "https://i.redditmedia.com/C0edo3GQfqJC44uCCdDXoJxmXvEmAU9sM203mc3SVlE.jpg?fit=crop&amp;crop=faces%2Centropy&amp;arh=2&amp;w=216&amp;s=8a3dc6712fcab694aac7530667513fb3",
                    "width": 216,
                    "height": 308
                  },
                  {
                    "url": "https://i.redditmedia.com/C0edo3GQfqJC44uCCdDXoJxmXvEmAU9sM203mc3SVlE.jpg?fit=crop&amp;crop=faces%2Centropy&amp;arh=2&amp;w=320&amp;s=c621b29e7df0cf84ff759ffe2073b97b",
                    "width": 320,
                    "height": 457
                  },
                  {
                    "url": "https://i.redditmedia.com/C0edo3GQfqJC44uCCdDXoJxmXvEmAU9sM203mc3SVlE.jpg?fit=crop&amp;crop=faces%2Centropy&amp;arh=2&amp;w=640&amp;s=c88579a3d14cb61f09f9dbed7708113f",
                    "width": 640,
                    "height": 914
                  }
                ],
                "variants": {},
                "id": "0IHhsbE8KmqnVPcTCTurFJ6FYWSDpOBeS5OFT-jVP6g"
              }
            ]
          },
          "num_comments": 0,
          "thumbnail": "http://b.thumbs.redditmedia.com/M_IZQFt_ZZgpQh1yU0zIQUUNzwpKWIN9X35bZTdnC3U.jpg",
          "subreddit_id": "t5_2qh0s",
          "hide_score": false,
          "edited": false,
          "link_flair_css_class": null,
          "author_flair_css_class": "artist",
          "downs": 0,
          "secure_media_embed": {},
          "saved": false,
          "removal_reason": null,
          "post_hint": "link",
          "stickied": false,
          "from": null,
          "is_self": false,
          "from_id": null,
          "permalink": "/r/comics/comments/3iled7/payback/",
          "name": "t3_3iled7",
          "created": 1440684395.0,
          "url": "http://lolnein.com/2013/07/02/payback/",
          "author_flair_text": "lolnein",
          "quarantine": false,
          "title": "Payback",
          "created_utc": 1440680795.0,
          "distinguished": null,
          "mod_reports": [],
          "visited": false,
          "num_reports": null,
          "ups": 7
        }
      },
      {
        "kind": "t3",
        "data": {
          "domain": "plancomic.com",
          "banned_by": null,
          "media_embed": {},
          "subreddit": "comics",
          "selftext_html": null,
          "selftext": "",
          "likes": null,
          "suggested_sort": null,
          "user_reports": [],
          "secure_media": null,
          "link_flair_text": null,
          "id": "3ildnb",
          "from_kind": null,
          "gilded": 0,
          "archived": false,
          "clicked": false,
          "report_reasons": null,
          "author": "Ajcam21",
          "media": null,
          "score": 7,
          "approved_by": null,
          "over_18": false,
          "hidden": false,
          "preview": {
            "images": [
              {
                "source": {
                  "url": "https://i.redditmedia.com/tpQcariz5BgHzzHlzSxO7eT7e8QdD-KwsdDvfSFJcAk.jpg?s=2dd7414c13d160901cb26d71e90568f6",
                  "width": 972,
                  "height": 324
                },
                "resolutions": [
                  {
                    "url": "https://i.redditmedia.com/tpQcariz5BgHzzHlzSxO7eT7e8QdD-KwsdDvfSFJcAk.jpg?fit=crop&amp;crop=faces%2Centropy&amp;arh=2&amp;w=108&amp;s=bfcbb19ffe99e1b2c00f01ee66a00aa9",
                    "width": 108,
                    "height": 36
                  },
                  {
                    "url": "https://i.redditmedia.com/tpQcariz5BgHzzHlzSxO7eT7e8QdD-KwsdDvfSFJcAk.jpg?fit=crop&amp;crop=faces%2Centropy&amp;arh=2&amp;w=216&amp;s=532709dab94d8f751f20447058ca7c52",
                    "width": 216,
                    "height": 72
                  },
                  {
                    "url": "https://i.redditmedia.com/tpQcariz5BgHzzHlzSxO7eT7e8QdD-KwsdDvfSFJcAk.jpg?fit=crop&amp;crop=faces%2Centropy&amp;arh=2&amp;w=320&amp;s=43c7df6491b618890078a14a08e51a38",
                    "width": 320,
                    "height": 106
                  },
                  {
                    "url": "https://i.redditmedia.com/tpQcariz5BgHzzHlzSxO7eT7e8QdD-KwsdDvfSFJcAk.jpg?fit=crop&amp;crop=faces%2Centropy&amp;arh=2&amp;w=640&amp;s=4b9aa10414d2691cad8c816400e3f514",
                    "width": 640,
                    "height": 213
                  },
                  {
                    "url": "https://i.redditmedia.com/tpQcariz5BgHzzHlzSxO7eT7e8QdD-KwsdDvfSFJcAk.jpg?fit=crop&amp;crop=faces%2Centropy&amp;arh=2&amp;w=960&amp;s=623eb38a7de9b499629c517cafa77a68",
                    "width": 960,
                    "height": 320
                  }
                ],
                "variants": {},
                "id": "K-nbDPm8YM7xVYJjRc854uyu6jzdCQ00dHB0ZHDZYOg"
              }
            ]
          },
          "num_comments": 0,
          "thumbnail": "http://b.thumbs.redditmedia.com/i7qPUQgKZeYPWIAKCGLeGk2SJM8fzPN2QZd0svn_ZKs.jpg",
          "subreddit_id": "t5_2qh0s",
          "hide_score": false,
          "edited": false,
          "link_flair_css_class": null,
          "author_flair_css_class": null,
          "downs": 0,
          "secure_media_embed": {},
          "saved": false,
          "removal_reason": null,
          "post_hint": "link",
          "stickied": false,
          "from": null,
          "is_self": false,
          "from_id": null,
          "permalink": "/r/comics/comments/3ildnb/new_franchise/",
          "name": "t3_3ildnb",
          "created": 1440709207.0,
          "url": "http://www.plancomic.com/?comic=new-franchise",
          "author_flair_text": null,
          "quarantine": false,
          "title": "New Franchise",
          "created_utc": 1440680407.0,
          "distinguished": null,
          "mod_reports": [],
          "visited": false,
          "num_reports": null,
          "ups": 7
        }
      },
      {
        "kind": "t3",
        "data": {
          "domain": "magictourbus.tumblr.com",
          "banned_by": null,
          "media_embed": {},
          "subreddit": "comics",
          "selftext_html": null,
          "selftext": "",
          "likes": null,
          "suggested_sort": null,
          "user_reports": [],
          "secure_media": null,
          "link_flair_text": null,
          "id": "3ins0w",
          "from_kind": null,
          "gilded": 0,
          "archived": false,
          "clicked": false,
          "report_reasons": null,
          "author": "gleantheaspect",
          "media": null,
          "score": 1,
          "approved_by": null,
          "over_18": false,
          "hidden": false,
          "preview": {
            "images": [
              {
                "source": {
                  "url": "https://i.redditmedia.com/EXybhhxgl61jOVoKqOSOd20lhi6_YnjC-HIpjGRxjDw.jpg?s=ae2d82ef888b71d6b6baacb3ae2107c5",
                  "width": 500,
                  "height": 375
                },
                "resolutions": [
                  {
                    "url": "https://i.redditmedia.com/EXybhhxgl61jOVoKqOSOd20lhi6_YnjC-HIpjGRxjDw.jpg?fit=crop&amp;crop=faces%2Centropy&amp;arh=2&amp;w=108&amp;s=4da65fe28115b531f129c6653b107670",
                    "width": 108,
                    "height": 81
                  },
                  {
                    "url": "https://i.redditmedia.com/EXybhhxgl61jOVoKqOSOd20lhi6_YnjC-HIpjGRxjDw.jpg?fit=crop&amp;crop=faces%2Centropy&amp;arh=2&amp;w=216&amp;s=2d96a69773ccb62d10df390287071467",
                    "width": 216,
                    "height": 162
                  },
                  {
                    "url": "https://i.redditmedia.com/EXybhhxgl61jOVoKqOSOd20lhi6_YnjC-HIpjGRxjDw.jpg?fit=crop&amp;crop=faces%2Centropy&amp;arh=2&amp;w=320&amp;s=f45991df6bc62e0bffda5a6506cf6e39",
                    "width": 320,
                    "height": 240
                  }
                ],
                "variants": {},
                "id": "zbE6L5CtE0DVGFbXNTCw9QuT00czazld-wl_Daa9bh8"
              }
            ]
          },
          "num_comments": 0,
          "thumbnail": "http://b.thumbs.redditmedia.com/T_9JumWbewZgV1ZPXylZq96ofeFxN0P_yV18y9Wx5To.jpg",
          "subreddit_id": "t5_2qh0s",
          "hide_score": false,
          "edited": false,
          "link_flair_css_class": null,
          "author_flair_css_class": null,
          "downs": 0,
          "secure_media_embed": {},
          "saved": false,
          "removal_reason": null,
          "post_hint": "link",
          "stickied": false,
          "from": null,
          "is_self": false,
          "from_id": null,
          "permalink": "/r/comics/comments/3ins0w/true_facts/",
          "name": "t3_3ins0w",
          "created": 1440746423.0,
          "url": "http://magictourbus.tumblr.com/post/127733224466/true-facts",
          "author_flair_text": null,
          "quarantine": false,
          "title": "True Facts",
          "created_utc": 1440717623.0,
          "distinguished": null,
          "mod_reports": [],
          "visited": false,
          "num_reports": null,
          "ups": 1
        }
      },
      {
        "kind": "t3",
        "data": {
          "domain": "pixton.com",
          "banned_by": null,
          "media_embed": {},
          "subreddit": "comics",
          "selftext_html": null,
          "selftext": "",
          "likes": null,
          "suggested_sort": null,
          "user_reports": [],
          "secure_media": null,
          "link_flair_text": null,
          "id": "3imwu9",
          "from_kind": null,
          "gilded": 0,
          "archived": false,
          "clicked": false,
          "report_reasons": null,
          "author": "billymcfarland",
          "media": null,
          "score": 2,
          "approved_by": null,
          "over_18": false,
          "hidden": false,
          "preview": {
            "images": [
              {
                "source": {
                  "url": "https://i.redditmedia.com/QGrRjjrlwcZJpsDNuKHT9iEWivKbP272FpIr5aCVVJA.jpg?s=b8cdd92df409abf8a8ac4fc0224c9e44",
                  "width": 295,
                  "height": 300
                },
                "resolutions": [
                  {
                    "url": "https://i.redditmedia.com/QGrRjjrlwcZJpsDNuKHT9iEWivKbP272FpIr5aCVVJA.jpg?fit=crop&amp;crop=faces%2Centropy&amp;arh=2&amp;w=108&amp;s=b19b9ef22e3c31eaecf809f4d4859291",
                    "width": 108,
                    "height": 109
                  },
                  {
                    "url": "https://i.redditmedia.com/QGrRjjrlwcZJpsDNuKHT9iEWivKbP272FpIr5aCVVJA.jpg?fit=crop&amp;crop=faces%2Centropy&amp;arh=2&amp;w=216&amp;s=dae0b90eec3b5c2b19edb8d8232a92f3",
                    "width": 216,
                    "height": 219
                  }
                ],
                "variants": {},
                "id": "d7Q3B4b_gfJ8FYer8hHC4RHC7J5FZ9I5z-ZlCmMGpCA"
              }
            ]
          },
          "num_comments": 0,
          "thumbnail": "http://b.thumbs.redditmedia.com/LF5s0yUvmZe43mc6K2aU8uuSBDKr2GpsAzePZm6IfDQ.jpg",
          "subreddit_id": "t5_2qh0s",
          "hide_score": false,
          "edited": false,
          "link_flair_css_class": null,
          "author_flair_css_class": null,
          "downs": 0,
          "secure_media_embed": {},
          "saved": false,
          "removal_reason": null,
          "post_hint": "link",
          "stickied": false,
          "from": null,
          "is_self": false,
          "from_id": null,
          "permalink": "/r/comics/comments/3imwu9/mr_fantastictrue_love/",
          "name": "t3_3imwu9",
          "created": 1440732850.0,
          "url": "http://www.pixton.com/comic-strip/okhwwdyl",
          "author_flair_text": null,
          "quarantine": false,
          "title": "Mr Fantastic-True Love",
          "created_utc": 1440704050.0,
          "distinguished": null,
          "mod_reports": [],
          "visited": false,
          "num_reports": null,
          "ups": 2
        }
      },
      {
        "kind": "t3",
        "data": {
          "domain": "ifightcrime.squareplanetcomics.com",
          "banned_by": null,
          "media_embed": {},
          "subreddit": "comics",
          "selftext_html": null,
          "selftext": "",
          "likes": null,
          "suggested_sort": null,
          "user_reports": [],
          "secure_media": null,
          "link_flair_text": null,
          "id": "3imu1i",
          "from_kind": null,
          "gilded": 0,
          "archived": false,
          "clicked": false,
          "report_reasons": null,
          "author": "Blastosaurus",
          "media": null,
          "score": 2,
          "approved_by": null,
          "over_18": false,
          "hidden": false,
          "preview": {
            "images": [
              {
                "source": {
                  "url": "https://i.redditmedia.com/JCIrUNhamEstv0vuRil6CoJp29sa0LvfmqsrYpqBSFM.jpg?s=7ca76f1f6f0aac9493c33a33af3f6c90",
                  "width": 150,
                  "height": 150
                },
                "resolutions": [
                  {
                    "url": "https://i.redditmedia.com/JCIrUNhamEstv0vuRil6CoJp29sa0LvfmqsrYpqBSFM.jpg?fit=crop&amp;crop=faces%2Centropy&amp;arh=2&amp;w=108&amp;s=76ced2facf0297125c0916823ebf1469",
                    "width": 108,
                    "height": 108
                  }
                ],
                "variants": {},
                "id": "pJVEGARaLTaor9IWfMhC3G52_OVF-Q9Pn3863K-XBvc"
              }
            ]
          },
          "num_comments": 0,
          "thumbnail": "http://b.thumbs.redditmedia.com/kAe8oqIQpx1TeWWUNRoBKv6yPRLlG6Yyne9pGS-pQDc.jpg",
          "subreddit_id": "t5_2qh0s",
          "hide_score": false,
          "edited": false,
          "link_flair_css_class": null,
          "author_flair_css_class": null,
          "downs": 0,
          "secure_media_embed": {},
          "saved": false,
          "removal_reason": null,
          "post_hint": "link",
          "stickied": false,
          "from": null,
          "is_self": false,
          "from_id": null,
          "permalink": "/r/comics/comments/3imu1i/what_i_like_about_bojack_horseman/",
          "name": "t3_3imu1i",
          "created": 1440731607.0,
          "url": "http://ifightcrime.squareplanetcomics.com/comic/ifc1720/",
          "author_flair_text": null,
          "quarantine": false,
          "title": "What I Like About Bojack Horseman",
          "created_utc": 1440702807.0,
          "distinguished": null,
          "mod_reports": [],
          "visited": false,
          "num_reports": null,
          "ups": 2
        }
      },
      {
        "kind": "t3",
        "data": {
          "domain": "tapastic.com",
          "banned_by": null,
          "media_embed": {},
          "subreddit": "comics",
          "selftext_html": null,
          "selftext": "",
          "likes": null,
          "suggested_sort": null,
          "user_reports": [],
          "secure_media": null,
          "link_flair_text": null,
          "id": "3im9f7",
          "from_kind": null,
          "gilded": 0,
          "archived": false,
          "clicked": false,
          "report_reasons": null,
          "author": "min_roh",
          "media": null,
          "score": 3,
          "approved_by": null,
          "over_18": false,
          "hidden": false,
          "preview": {
            "images": [
              {
                "source": {
                  "url": "https://i.redditmedia.com/-VkTbv-FrjKIASdX4C5wxgXUbyV26H_AyBWmQpb938I.jpg?s=2eaccc819915ae82ce3f170fdb20d78d",
                  "width": 600,
                  "height": 315
                },
                "resolutions": [
                  {
                    "url": "https://i.redditmedia.com/-VkTbv-FrjKIASdX4C5wxgXUbyV26H_AyBWmQpb938I.jpg?fit=crop&amp;crop=faces%2Centropy&amp;arh=2&amp;w=108&amp;s=4f0a78ff2f1d92f5e91c519661806748",
                    "width": 108,
                    "height": 56
                  },
                  {
                    "url": "https://i.redditmedia.com/-VkTbv-FrjKIASdX4C5wxgXUbyV26H_AyBWmQpb938I.jpg?fit=crop&amp;crop=faces%2Centropy&amp;arh=2&amp;w=216&amp;s=f2a30f22160a8efa645465265c6d5fe2",
                    "width": 216,
                    "height": 113
                  },
                  {
                    "url": "https://i.redditmedia.com/-VkTbv-FrjKIASdX4C5wxgXUbyV26H_AyBWmQpb938I.jpg?fit=crop&amp;crop=faces%2Centropy&amp;arh=2&amp;w=320&amp;s=05100f8ba7a6908254357dccc4bccbf5",
                    "width": 320,
                    "height": 168
                  }
                ],
                "variants": {},
                "id": "smapGiNUDGWxAx-1G171yhXXULDI6L5BoyvNfjPhcuM"
              }
            ]
          },
          "num_comments": 0,
          "thumbnail": "http://b.thumbs.redditmedia.com/b4PZLAl5qLZghT8Ny9QozyL8XxKMJFrDVsY3-ZVjIIE.jpg",
          "subreddit_id": "t5_2qh0s",
          "hide_score": false,
          "edited": false,
          "link_flair_css_class": null,
          "author_flair_css_class": null,
          "downs": 0,
          "secure_media_embed": {},
          "saved": false,
          "removal_reason": null,
          "post_hint": "link",
          "stickied": false,
          "from": null,
          "is_self": false,
          "from_id": null,
          "permalink": "/r/comics/comments/3im9f7/the_lion_give_your_best_and_dont_be_obsessive/",
          "name": "t3_3im9f7",
          "created": 1440723208.0,
          "url": "http://tapastic.com/episode/185010",
          "author_flair_text": null,
          "quarantine": false,
          "title": "The Lion: Give your best and don\u2019t be obsessive with the results",
          "created_utc": 1440694408.0,
          "distinguished": null,
          "mod_reports": [],
          "visited": false,
          "num_reports": null,
          "ups": 3
        }
      },
      {
        "kind": "t3",
        "data": {
          "domain": "newgrounds.com",
          "banned_by": null,
          "media_embed": {},
          "subreddit": "comics",
          "selftext_html": null,
          "selftext": "",
          "likes": null,
          "suggested_sort": null,
          "user_reports": [],
          "secure_media": null,
          "link_flair_text": null,
          "id": "3inmi3",
          "from_kind": null,
          "gilded": 0,
          "archived": false,
          "clicked": false,
          "report_reasons": null,
          "author": "Paradise-san",
          "media": null,
          "score": 0,
          "approved_by": null,
          "over_18": false,
          "hidden": false,
          "preview": {
            "images": [
              {
                "source": {
                  "url": "https://i.redditmedia.com/AUhiICsgKhmzYeePE6X4hKYrmiatdJBJeYQZ7loUS_Y.jpg?s=3c8ddec2207b6a247387ce633d37cc49",
                  "width": 590,
                  "height": 181
                },
                "resolutions": [
                  {
                    "url": "https://i.redditmedia.com/AUhiICsgKhmzYeePE6X4hKYrmiatdJBJeYQZ7loUS_Y.jpg?fit=crop&amp;crop=faces%2Centropy&amp;arh=2&amp;w=108&amp;s=73de10c7dbf972928344123cd15e7ded",
                    "width": 108,
                    "height": 33
                  },
                  {
                    "url": "https://i.redditmedia.com/AUhiICsgKhmzYeePE6X4hKYrmiatdJBJeYQZ7loUS_Y.jpg?fit=crop&amp;crop=faces%2Centropy&amp;arh=2&amp;w=216&amp;s=ea7baf9940c7733c8d4b26ab768624a5",
                    "width": 216,
                    "height": 66
                  },
                  {
                    "url": "https://i.redditmedia.com/AUhiICsgKhmzYeePE6X4hKYrmiatdJBJeYQZ7loUS_Y.jpg?fit=crop&amp;crop=faces%2Centropy&amp;arh=2&amp;w=320&amp;s=b0a72a05687804ef78d2f5b86451dc4a",
                    "width": 320,
                    "height": 98
                  }
                ],
                "variants": {},
                "id": "-8ylAL3GB1qh09OQqREP5Yn_0zXvKp-ahkv6NjggAYg"
              }
            ]
          },
          "num_comments": 0,
          "thumbnail": "http://b.thumbs.redditmedia.com/vegD-I-BXkpUZ7cxF-AHV2w3y4gG5iQmlF5X-ww7YVI.jpg",
          "subreddit_id": "t5_2qh0s",
          "hide_score": false,
          "edited": false,
          "link_flair_css_class": null,
          "author_flair_css_class": null,
          "downs": 0,
          "secure_media_embed": {},
          "saved": false,
          "removal_reason": null,
          "post_hint": "link",
          "stickied": false,
          "from": null,
          "is_self": false,
          "from_id": null,
          "permalink": "/r/comics/comments/3inmi3/asian_food/",
          "name": "t3_3inmi3",
          "created": 1440743825.0,
          "url": "http://www.newgrounds.com/art/view/jamespara/asian-food",
          "author_flair_text": null,
          "quarantine": false,
          "title": "Asian food",
          "created_utc": 1440715025.0,
          "distinguished": null,
          "mod_reports": [],
          "visited": false,
          "num_reports": null,
          "ups": 0
        }
      }
    ],
    "after": "t3_3inmi3",
    "before": "t3_3ingwq"
  }
}